wordgoblin/__init__.py
wordgoblin/goblin.py
wordgoblin/data/en_dict.json
wordgoblin-1.1.0.dist-info/METADATA
wordgoblin-1.1.0.dist-info/WHEEL
wordgoblin-1.1.0.dist-info/licenses/LICENSE
wordgoblin-1.1.0.dist-info/RECORD
