Metadata-Version: 2.3
Name: wordgoblin
Version: 1.1.0
Summary: A lightweight word finder.
Project-URL: Homepage, https://github.com/ian-nai/wordgoblin
Project-URL: Bug Tracker, https://github.com/ian-nai/wordgoblin/issues
Author-email: Ian Goodale <ianpgoodale@gmail.com>
License: GNU GENERAL PUBLIC LICENSE
License-File: LICENSE
Classifier: License :: OSI Approved :: GNU General Public License v3 (GPLv3)
Classifier: Operating System :: OS Independent
Classifier: Programming Language :: Python :: 3
Requires-Python: >=3.7
